<?xml version="1.0" encoding="UTF-8"?>
<newsSources>
	<newsSource>
		<name>BBC - News</name>
		<url>http://feeds.bbci.co.uk/news/rss.xml</url>
		<order>0</order>
		<active>true</active>
	</newsSource>
	<newsSource>
		<name>CNN.com - World</name>
		<url>http://rss.cnn.com/rss/cnn_world.rss</url>
		<order>1</order>
		<active>true</active>
	</newsSource>
	<newsSource>
		<name>CNN.com - Health</name>
		<url>http://rss.cnn.com/rss/cnn_health.rss</url>
		<order>2</order>
		<group>1</group>
	</newsSource>
	<newsSource>
		<name>CNN.com - Tech</name>
		<url>http://rss.cnn.com/rss/cnn_tech.rss</url>
		<order>3</order>
		<group>1</group>
	</newsSource>
	<newsSource>
		<name>CNN.com - Politics</name>
		<url>http://rss.cnn.com/rss/cnn_allpolitics.rss</url>
		<order>4</order>
		<group>1</group>
	</newsSource>
</newsSources>